{
	"__comment":"Designed by GeForceLegend",
	"ambientocclusion":false,
	"textures":{
		"cross":"block/brown_mushroom",
		"particle":"block/brown_mushroom"
	},
	"elements":[
		{
			"from":[7,0,7],
			"to":[9,4,9],
			"rotation":{"angle":-45,"axis":"y","origin":[8,3,8]},
			"faces":{
				"north":{"uv":[7,12.005,9,16],"texture":"#cross"},
				"east":{"uv":[7,12.005,9,16],"texture":"#cross"},
				"south":{"uv":[7,12.005,9,16],"texture":"#cross"},
				"west":{"uv":[7,12.005,9,16],"texture":"#cross"},
				"down":{"uv":[7,14.0075,9,16],"texture":"#cross","cullface":"down"}
			}
		},
		{
			"from":[7,2,5],
			"to":[9,5,11],
			"rotation":{"angle":-45,"axis":"y","origin":[8,3,8]},
			"faces":{
				"north":{"uv":[11,11.0037,9.0012,14],"texture":"#cross"},
				"east":{"uv":[7,11.0037,11,14],"texture":"#cross"},
				"south":{"uv":[6,11.0037,8,14],"texture":"#cross"},
				"west":{"uv":[10,11.0037,6,14],"texture":"#cross"},
				"up":{"uv":[10,13,5,11.0037],"rotation":90,"texture":"#cross"},
				"down":{"uv":[5,11.0037,11,13],"rotation":90,"texture":"#cross"}
			}
		},
		{
			"from":[5,2,7],
			"to":[11,5,9],
			"rotation":{"angle":-45,"axis":"y","origin":[8,3,8]},
			"faces":{
				"north":{"uv":[7,11.0037,11,14],"texture":"#cross"},
				"east":{"uv":[6,11.0037,8,14],"texture":"#cross"},
				"south":{"uv":[10,11.0037,6,14],"texture":"#cross"},
				"west":{"uv":[11,11.0037,9.0012,14],"texture":"#cross"},
				"up":{"uv":[10,13,5,11.0037],"texture":"#cross"},
				"down":{"uv":[5,11.0037,11,13],"rotation":180,"texture":"#cross"}
			}
		},
		{
			"from":[6,2.01,6],
			"to":[10,5,10],
			"rotation":{"angle":-45,"axis":"y","origin":[8,3,8]},
			"faces":{
				"north":{"uv":[6,13.1,10,14],"texture":"#cross"},
				"east":{"uv":[7,14,10,10.0025],"rotation":90,"texture":"#cross"},
				"south":{"uv":[10,10.0025,6,13],"texture":"#cross"},
				"west":{"uv":[11,11.0037,7,14],"texture":"#cross"},
				"up":{"uv":[10,14,6,10.0025],"texture":"#cross"},
				"down":{"uv":[6,14,10,10.0025],"rotation":180,"texture":"#cross"}
			}
		},
		{
			"from":[6,5,7],
			"to":[10,6,9],
			"rotation":{"angle":-45,"axis":"y","origin":[8,3,8]},
			"faces":{
				"north":{"uv":[6,10.1,8,11],"texture":"#cross"},
				"east":{"uv":[6,10.1,8,11],"texture":"#cross"},
				"south":{"uv":[6,10.1,8,11],"texture":"#cross"},
				"west":{"uv":[6,10.1,8,11],"texture":"#cross"},
				"up":{"uv":[6,10.1,8,11],"texture":"#cross"}
			}
		},
		{
			"from":[7,5,6],
			"to":[9,6,10],
			"rotation":{"angle":-45,"axis":"y","origin":[8,3,8]},
			"faces":{
				"north":{"uv":[6,10.1,8,11],"texture":"#cross"},
				"east":{"uv":[6,10.1,8,11],"texture":"#cross"},
				"south":{"uv":[6,10.1,8,11],"texture":"#cross"},
				"west":{"uv":[6,10.1,8,11],"texture":"#cross"},
				"up":{"uv":[6,10.1,8,11],"texture":"#cross"}
			}
		}
	]
}